smartdiffer/__init__.py
smartdiffer/cli.py
smartdiffer/config.py
smartdiffer/diffchecker.py
smartdiffer/etherscan_api.py
smartdiffer/srccode.py
smartdiffer-0.1.5.dist-info/LICENSE
smartdiffer-0.1.5.dist-info/METADATA
smartdiffer-0.1.5.dist-info/WHEEL
smartdiffer-0.1.5.dist-info/entry_points.txt
smartdiffer-0.1.5.dist-info/top_level.txt
smartdiffer-0.1.5.dist-info/RECORD
