Metadata-Version: 2.1
Name: smartdiffer
Version: 0.1.5
Summary: Tool to compare smart contracts source code
Home-page: https://github.com/skalermo/smartdiffer
Author: skalermo (Roman Moskalenko)
Author-email: skalermo@gmail.com
Keywords: python,etherscan-api,diffchecker
Classifier: Development Status :: 1 - Planning
Classifier: Intended Audience :: Developers
Classifier: Programming Language :: Python :: 3
Classifier: Operating System :: Unix
Classifier: Operating System :: MacOS :: MacOS X
Classifier: Operating System :: Microsoft :: Windows
License-File: LICENSE
Requires-Dist: requests (>=2.26.0)
Requires-Dist: py-etherscan-api (>=0.8.0)
